LICENSE
MANIFEST.in
README.rst
setup.py
r_lint/__init__.py
r_lint/builder.py
r_lint/lint.py
r_lint.egg-info/PKG-INFO
r_lint.egg-info/SOURCES.txt
r_lint.egg-info/dependency_links.txt
r_lint.egg-info/requires.txt
r_lint.egg-info/top_level.txt
scripts/r-lint