Metadata-Version: 1.0
Name: r-lint
Version: 0.1.0
Summary: Small linting tool for R containers at QBiC
Home-page: UNKNOWN
Author: Sven Fillinger
Author-email: sven.fillinger@qbic.uni-tuebingen.de
License: MIT License
